diffydes/__init__.py
diffydes/exp.py
diffydes-0.0.25.dist-info/METADATA
diffydes-0.0.25.dist-info/WHEEL
diffydes-0.0.25.dist-info/top_level.txt
diffydes-0.0.25.dist-info/RECORD
